hiraishin/__init__.py
hiraishin/cli.py
hiraishin/models/__init__.py
hiraishin/models/base_model.py
hiraishin/models/utils.py
hiraishin/schema/__init__.py
hiraishin/schema/pydantic.py
hiraishin/schema/typing.py
hiraishin/utils.py
hiraishin-0.2.1.dist-info/entry_points.txt
hiraishin-0.2.1.dist-info/LICENSE
hiraishin-0.2.1.dist-info/WHEEL
hiraishin-0.2.1.dist-info/METADATA
hiraishin-0.2.1.dist-info/RECORD
