Metadata-Version: 2.1
Name: hiraishin
Version: 0.2.1
Summary: A thin PyTorch-Lightning wrapper for building configuration-based DL pipelines with Hydra.
License: Apache 2.0
Author: So Uchida
Author-email: s.aiueo32@gmail.com
Requires-Python: >=3.8,<4.0
Classifier: License :: Other/Proprietary License
Classifier: Programming Language :: Python :: 3
Classifier: Programming Language :: Python :: 3.8
Classifier: Programming Language :: Python :: 3.9
Classifier: Programming Language :: Python :: 3.10
Requires-Dist: click (>=8.0.0,<9.0.0)
Requires-Dist: hydra-core (==1.1.1)
Requires-Dist: overrides (>=3.1.0,<4.0.0)
Requires-Dist: pydantic (>=1.8.1,<2.0.0)
Requires-Dist: pytorch-lightning (>=1.6.0,<2.0.0)
